setup.cfg
setup.py
dell_storagecenter_driver/__init__.py
dell_storagecenter_driver/dell_storagecenter_api.py
dell_storagecenter_driver/dell_storagecenter_blockdevice.py
dell_storagecenter_driver/iscsi_utils.py
dell_storagecenter_driver/test_dell_sc.py
dell_storagecenter_driver.egg-info/PKG-INFO
dell_storagecenter_driver.egg-info/SOURCES.txt
dell_storagecenter_driver.egg-info/dependency_links.txt
dell_storagecenter_driver.egg-info/requires.txt
dell_storagecenter_driver.egg-info/top_level.txt