Metadata-Version: 1.1
Name: dell-storagecenter-driver
Version: 1.0
Summary: Dell Storage Center Plugin for Flocker
Home-page: https://github.com/dellstorage/storagecenter-flocker-driver
Author: Sean McGinnis
Author-email: sean_mcginnis@dell.com
License: Apache 2.0
Download-URL: https://github.com/dellstorage/storagecenter-flocker-driver/tarball/1.0
Keywords: backend,plugin,flocker,docker,python
Platform: UNKNOWN
Classifier: Development Status :: 4 - Beta
Classifier: Programming Language :: Python :: 2.7
